udiph
