Metadata-Version: 2.1
Name: udiph
Version: 0.0.2
Summary: Uniform distributed persistent homology.
Home-page: https://github.com/Antonio-Leitao/udiph
Author: Antonio Leitao
Author-email: aleitao@novaims.unl.pt
License: UNKNOWN
Platform: UNKNOWN
Classifier: Programming Language :: Python :: 3
Classifier: License :: OSI Approved :: MIT License
Classifier: Operating System :: OS Independent
Requires-Python: >=3.6
